{"trains":[{"id":"SNCF_ACCES_CLOUD:VehicleJourney::b1d88db4-850f-4031-969d-4c3fdd755f9b:LOC","ligne":"RER E","mission":"HAVA","destination":"Haussmann Saint-Lazare","arrivee":"11:04:53","arriveeReelle":"11:05:12","status":"onTime","difference":"19 secondes de retard"},{"id":"SNCF_ACCES_CLOUD:VehicleJourney::6a52221e-04b9-4372-804d-03ba736005f1:LOC","ligne":"RER E","mission":"TAVA","destination":"Gare de Tournan","arrivee":"11:24:03","arriveeReelle":"11:25:33","status":"onTime","difference":"1 minutes et 30 secondes de retard"}]}